<annotation>
  <folder>Line</folder>
  <filename>Line_Dataset-059.jpg</filename>
  <source>
    <database>Unknown</database>
    <annotation>Unknown</annotation>
    <image>Unknown</image>
  </source>
  <size>
    <width>2182</width>
    <height>1538</height>
    <depth></depth>
  </size>
  <segmented>0</segmented>
  <object>
    <name>line</name>
    <truncated>0</truncated>
    <occluded>0</occluded>
    <difficult>0</difficult>
    <bndbox>
      <xmin>443.29</xmin>
      <ymin>411.09</ymin>
      <xmax>935.03</xmax>
      <ymax>683.52</ymax>
    </bndbox>
    <attributes>
      <attribute>
        <name>rotation</name>
        <value>0.0</value>
      </attribute>
    </attributes>
  </object>
  <object>
    <name>line</name>
    <truncated>0</truncated>
    <occluded>0</occluded>
    <difficult>0</difficult>
    <bndbox>
      <xmin>632.75</xmin>
      <ymin>659.99</ymin>
      <xmax>835.96</xmax>
      <ymax>782.59</ymax>
    </bndbox>
    <attributes>
      <attribute>
        <name>rotation</name>
        <value>0.0</value>
      </attribute>
    </attributes>
  </object>
  <object>
    <name>line</name>
    <truncated>0</truncated>
    <occluded>0</occluded>
    <difficult>0</difficult>
    <bndbox>
      <xmin>764.01</xmin>
      <ymin>760.3</ymin>
      <xmax>858.25</xmax>
      <ymax>818.5</ymax>
    </bndbox>
    <attributes>
      <attribute>
        <name>rotation</name>
        <value>0.0</value>
      </attribute>
    </attributes>
  </object>
  <object>
    <name>line</name>
    <truncated>0</truncated>
    <occluded>0</occluded>
    <difficult>0</difficult>
    <bndbox>
      <xmin>837.08</xmin>
      <ymin>929.95</ymin>
      <xmax>1067.53</xmax>
      <ymax>1036.45</ymax>
    </bndbox>
    <attributes>
      <attribute>
        <name>rotation</name>
        <value>0.0</value>
      </attribute>
    </attributes>
  </object>
</annotation>
